{"notes":[{"title":"222","content":"222","id":"2024-04-07T06:44:22.305Z"},{"title":"second note","content":"remix is awesome!","id":"2024-04-07T07:01:18.032Z"},{"title":"third note","content":"remix is awesome!","id":"2024-04-07T07:05:45.037Z"},{"title":"fourth note","content":"remiiiix","id":"2024-04-07T07:07:33.887Z"},{"title":"fivth note","content":"remiiix","id":"2024-04-07T07:07:57.421Z"},{"title":"new note","content":"noooteeeee","id":"2024-04-07T07:08:18.517Z"},{"title":"1","content":"1","id":"2024-04-07T07:11:58.157Z"},{"title":"11","content":"222","id":"2024-04-07T07:15:55.172Z"}]}